libpyl3s/__init__.py
libpyl3s/pyl3slib.py
libpyl3s-1.0.0.dist-info/METADATA
libpyl3s-1.0.0.dist-info/WHEEL
libpyl3s-1.0.0.dist-info/top_level.txt
libpyl3s-1.0.0.dist-info/RECORD
